beautiful_rainbow/__init__.py
beautiful_rainbow/beautiful_rainbow.py
beautiful_rainbow-1.0.0.dist-info/METADATA
beautiful_rainbow-1.0.0.dist-info/WHEEL
beautiful_rainbow-1.0.0.dist-info/top_level.txt
beautiful_rainbow-1.0.0.dist-info/RECORD
