Metadata-Version: 2.1
Name: beautiful-rainbow
Version: 1.0.0
Summary: A very basic package practice.
Home-page: UNKNOWN
Author: ilco
License: UNKNOWN
Platform: UNKNOWN
